cs_year_explorer/__init__.py
cs_year_explorer/main.py
cs_year_explorer/prompts.py
cs_year_explorer-2025.12.21200620.dist-info/METADATA
cs_year_explorer-2025.12.21200620.dist-info/WHEEL
cs_year_explorer-2025.12.21200620.dist-info/top_level.txt
cs_year_explorer-2025.12.21200620.dist-info/RECORD
