Metadata-Version: 2.4
Name: cs-year-explorer
Version: 2025.12.21200620
Summary: Access computer science history by year, including major breakthroughs, research papers, and technological advancements.
Author-email: cs-year-explorer <hi@eugene.plus>
License: MIT
Project-URL: Homepage, https://github.com/chigwell/cs-year-explorer
Requires-Python: >=3.9
Requires-Dist: langchain-llm7>=0.0.0
Requires-Dist: llmatch-messages>=0.0.0
Requires-Dist: langchain-core>=0.3.0
